setup.py
distributions_su/Binomialdistribution.py
distributions_su/Gaussiandistribution.py
distributions_su/Generaldistribution.py
distributions_su/__init__.py
distributions_su.egg-info/PKG-INFO
distributions_su.egg-info/SOURCES.txt
distributions_su.egg-info/dependency_links.txt
distributions_su.egg-info/not-zip-safe
distributions_su.egg-info/top_level.txt